picosapi/__init__.py
picosapi/picosapi.py
picosapi-0.5.2.dist-info/DESCRIPTION.rst
picosapi-0.5.2.dist-info/METADATA
picosapi-0.5.2.dist-info/RECORD
picosapi-0.5.2.dist-info/WHEEL
picosapi-0.5.2.dist-info/metadata.json
picosapi-0.5.2.dist-info/top_level.txt
